helixcore/__init__.py
helixcore/py.typed
helixcore/register.py
helixcore/event_loggers/__init__.py
helixcore/event_loggers/event_logger.py
helixcore/logger/__init__.py
helixcore/logger/log_level.py
helixcore/logger/yarn_logger.py
helixcore/progress_logger/__init__.py
helixcore/progress_logger/progress_log_metric.py
helixcore/progress_logger/progress_logger.py
helixcore/progress_logger/progress_logger_run.py
helixcore/structures/__init__.py
helixcore/structures/fhir_receiver/__init__.py
helixcore/structures/fhir_receiver/v2/__init__.py
helixcore/structures/fhir_receiver/v2/fhir_receiver_parameters.py
helixcore/structures/fhir_receiver/v2/structures/__init__.py
helixcore/structures/fhir_receiver/v2/structures/get_batch_error.py
helixcore/structures/fhir_receiver/v2/structures/get_batch_result.py
helixcore/utilities/__init__.py
helixcore/utilities/json_helpers.py
helixcore/utilities/api_helper/__init__.py
helixcore/utilities/api_helper/http_request.py
helixcore/utilities/api_helper/v2/__init__.py
helixcore/utilities/api_helper/v2/http_request.py
helixcore/utilities/api_helper/v2/test/__init__.py
helixcore/utilities/api_helper/v2/test/test_http_request.py
helixcore/utilities/async_helper/__init__.py
helixcore/utilities/async_helper/v1/__init__.py
helixcore/utilities/async_helper/v1/async_helper.py
helixcore/utilities/async_helper/v1/test/__init__.py
helixcore/utilities/async_helper/v1/test/test_async_helper.py
helixcore/utilities/async_pandas_udf/__init__.py
helixcore/utilities/async_pandas_udf/v1/__init__.py
helixcore/utilities/async_pandas_udf/v1/async_pandas_udf_parameters.py
helixcore/utilities/async_safe_buffer/__init__.py
helixcore/utilities/async_safe_buffer/v1/__init__.py
helixcore/utilities/async_safe_buffer/v1/async_safe_buffer.py
helixcore/utilities/async_safe_buffer/v1/test/__init__.py
helixcore/utilities/async_safe_buffer/v1/test/test_async_buffer.py
helixcore/utilities/aws/__init__.py
helixcore/utilities/aws/config.py
helixcore/utilities/aws/s3.py
helixcore-1.0.12.dist-info/LICENSE
helixcore-1.0.12.dist-info/METADATA
helixcore-1.0.12.dist-info/WHEEL
helixcore-1.0.12.dist-info/top_level.txt
helixcore-1.0.12.dist-info/RECORD
